fortios_xutils/__init__.py
fortios_xutils/api.py
fortios_xutils/cli.py
fortios_xutils/finder.py
fortios_xutils/firewall.py
fortios_xutils/netutils.py
fortios_xutils/network.py
fortios_xutils/parser.py
fortios_xutils/utils.py
fortios_xutils-0.4.2.dist-info/LICENSE.MIT
fortios_xutils-0.4.2.dist-info/METADATA
fortios_xutils-0.4.2.dist-info/WHEEL
fortios_xutils-0.4.2.dist-info/entry_points.txt
fortios_xutils-0.4.2.dist-info/top_level.txt
fortios_xutils-0.4.2.dist-info/RECORD
