Metadata-Version: 2.1
Name: fortios-xutils
Version: 0.4.2
Summary: Very experimental miscellaneous and extra utilities for fortios
Home-page: https://github.com/ssato/fortios-xutils
Author: Satoru SATOH
Author-email: satoru.satoh@gmail.com
Maintainer: Satoru SATOH
Maintainer-email: satoru.satoh@gmail.com
License: MIT
Project-URL: CI: Travis, https://travis-ci.org/ssato/fortios-xutils
Project-URL: Download, https://pypi.org/project/anyconfig-fortios-backend/
Project-URL: Download RPMs, https://copr.fedoraproject.org/coprs/ssato/extras/
Project-URL: Bug Tracker, https://github.com/ssato/fortios-xutils/issues
Project-URL: Source, https://github.com/ssato/fortios-xutils
Platform: any
Classifier: Development Status :: 4 - Beta
Classifier: Intended Audience :: Developers
Classifier: Programming Language :: Python
Classifier: Programming Language :: Python :: 3
Classifier: Programming Language :: Python :: 3.6
Classifier: Programming Language :: Python :: 3.7
Classifier: Programming Language :: Python :: 3.8
Classifier: Operating System :: OS Independent
Classifier: Topic :: Software Development :: Libraries :: Python Modules
Classifier: Topic :: Utilities
Classifier: License :: OSI Approved :: MIT License
Requires-Dist: PyYAML
Requires-Dist: anyconfig
Requires-Dist: anyconfig-fortios-backend
Requires-Dist: click
Requires-Dist: jmespath
Requires-Dist: netaddr
Requires-Dist: networkx
Requires-Dist: pandas
